ibmsecurity/__init__.py
ibmsecurity/appliance/__init__.py
ibmsecurity/appliance/ibmappliance.py
ibmsecurity/appliance/isamappliance.py
ibmsecurity/appliance/isamappliance_adminproxy.py
ibmsecurity/appliance/isdsappliance.py
ibmsecurity/appliance/isdsappliance_adminproxy.py
ibmsecurity/appliance/isvgappliance.py
ibmsecurity/appliance/isvgappliance_adminproxy.py
ibmsecurity/isam/__init__.py
ibmsecurity/isam/appliance.py
ibmsecurity/isam/application_logs.py
ibmsecurity/isam/event_log.py
ibmsecurity/isam/statistics.py
ibmsecurity/isam/aac/__init__.py
ibmsecurity/isam/aac/access_policy.py
ibmsecurity/isam/aac/advanced_configuration.py
ibmsecurity/isam/aac/attribute_matchers.py
ibmsecurity/isam/aac/attributes.py
ibmsecurity/isam/aac/database.py
ibmsecurity/isam/aac/extensions.py
ibmsecurity/isam/aac/mapping_rules.py
ibmsecurity/isam/aac/obligation_types.py
ibmsecurity/isam/aac/obligations.py
ibmsecurity/isam/aac/password_vault.py
ibmsecurity/isam/aac/risk_profiles.py
ibmsecurity/isam/aac/scim_custom_schema_extensions.py
ibmsecurity/isam/aac/user_info.py
ibmsecurity/isam/aac/access_control/__init__.py
ibmsecurity/isam/aac/access_control/policies.py
ibmsecurity/isam/aac/access_control/policy_attachments.py
ibmsecurity/isam/aac/access_control/policy_sets.py
ibmsecurity/isam/aac/api_protection/__init__.py
ibmsecurity/isam/aac/api_protection/clients.py
ibmsecurity/isam/aac/api_protection/definitions.py
ibmsecurity/isam/aac/api_protection/dynamic_clients.py
ibmsecurity/isam/aac/api_protection/dynamic_clients_migration.py
ibmsecurity/isam/aac/api_protection/grants.py
ibmsecurity/isam/aac/api_protection/grants_user.py
ibmsecurity/isam/aac/authentication/__init__.py
ibmsecurity/isam/aac/authentication/mechanism_types.py
ibmsecurity/isam/aac/authentication/mechanisms.py
ibmsecurity/isam/aac/authentication/policies.py
ibmsecurity/isam/aac/authentication/rsa_otp.py
ibmsecurity/isam/aac/authentication/rsa_otp/__init__.py
ibmsecurity/isam/aac/authentication/rsa_otp/all.py
ibmsecurity-2026.1.13.0.dist-info/licenses/LICENSE
ibmsecurity-2026.1.13.0.dist-info/METADATA
ibmsecurity-2026.1.13.0.dist-info/WHEEL
ibmsecurity-2026.1.13.0.dist-info/top_level.txt
ibmsecurity-2026.1.13.0.dist-info/RECORD
