Metadata-Version: 2.4
Name: ibmsecurity
Version: 2026.1.13.0
Summary: Idempotent functions for IBM Verify Appliance REST APIs
Home-page: 
Author: IBM
Author-email: IBM <secorch@wwpdl.vnet.ibm.com>
License-Expression: Apache-2.0
Project-URL: Homepage, https://github.com/IBM-Security/ibmsecurity
Project-URL: Bug Tracker, https://github.com/IBM-Security/ibmsecurity/issues
Classifier: Programming Language :: Python :: 3
Classifier: Operating System :: OS Independent
Classifier: Development Status :: 5 - Production/Stable
Classifier: Environment :: Console
Classifier: Intended Audience :: System Administrators
Classifier: Topic :: Software Development :: Build Tools
Requires-Python: >=3.9
License-File: LICENSE
Requires-Dist: filelock>=3.8.2
Requires-Dist: importlib-metadata
Requires-Dist: jsonschema>=4.10.0
Requires-Dist: packaging>=22.0
Requires-Dist: pathspec>=0.10.3
Requires-Dist: pyyaml>=6.0.2
Requires-Dist: requests
Requires-Dist: jmespath>=1.0.0
Requires-Dist: PyYAML
Requires-Dist: python-dateutil
Requires-Dist: cryptography>=36.0.0
Provides-Extra: docs
Requires-Dist: mkdocs; extra == "docs"
Requires-Dist: mkdocs-material; extra == "docs"
Requires-Dist: markdown-exec; extra == "docs"
Requires-Dist: mkdocstrings; extra == "docs"
Requires-Dist: pymdown-extensions; extra == "docs"
Requires-Dist: markdown_include; extra == "docs"
Provides-Extra: test
Requires-Dist: black; extra == "test"
Requires-Dist: coverage-enable-subprocess; extra == "test"
Requires-Dist: coverage[toml]>=6.4.4; extra == "test"
Requires-Dist: jmespath; extra == "test"
Requires-Dist: license-expression>=30.3.0; extra == "test"
Requires-Dist: mypy; extra == "test"
Requires-Dist: netaddr; extra == "test"
Requires-Dist: pip; extra == "test"
Requires-Dist: psutil; extra == "test"
Requires-Dist: pylint; extra == "test"
Requires-Dist: pytest>=7.2.2; extra == "test"
Requires-Dist: pytest-instafail>=0.5.0; extra == "test"
Requires-Dist: pytest-mock; extra == "test"
Requires-Dist: pytest-dotenv; extra == "test"
Requires-Dist: pytest-sugar; extra == "test"
Requires-Dist: pytest-xdist[psutil,setproctitle]>=2.1.0; extra == "test"
Requires-Dist: pytest-order; extra == "test"
Requires-Dist: tox>=4.0.0; extra == "test"
Requires-Dist: tox-extra>=2.1; extra == "test"
Requires-Dist: tox-uv>=1.25; extra == "test"
Requires-Dist: tox>=4.24.2; extra == "test"
Requires-Dist: types-jsonschema; extra == "test"
Requires-Dist: types-pyyaml; extra == "test"
Dynamic: author
Dynamic: license-file
